{
    "sourceFile": "src/components/Hero/TestimonialSection.jsx",
    "activeCommit": 0,
    "commits": [
        {
            "activePatchIndex": 8,
            "patches": [
                {
                    "date": 1759922531298,
                    "content": "Index: \n===================================================================\n--- \n+++ \n"
                },
                {
                    "date": 1759922770636,
                    "content": "Index: \n===================================================================\n--- \n+++ \n@@ -89,17 +89,21 @@\n               >\n                 {/* First set - include rating card */}\n                 {i < testimonials.length ? (\n                   i === 0 ? (\n-                    // Rating card\n-                    <div className=\"text-center\">\n-                      <p className=\"text-5xl font-bold text-gray-400\">4.9</p>\n-                      <div className=\"flex justify-center my-2\">\n-                        {[...Array(5)].map((_, starIndex) => (\n-                          <FaStar key={starIndex} className=\"text-green-500\" />\n-                        ))}\n+                    // Rating card - with same sizing as previous version\n+                    <div className=\"bg-white max-w-[50vh] p-6 shadow-sm text-center flex flex-col justify-between\">\n+                      <div>\n+                        <p className=\"text-5xl font-bold text-gray-400\">4.9</p>\n+                        <div className=\"flex justify-center my-2\">\n+                          {Array(5)\n+                            .fill(null)\n+                            .map((_, starIndex) => (\n+                              <FaStar key={starIndex} className=\"text-green-500\" />\n+                            ))}\n+                        </div>\n+                        <p className=\"text-sm text-gray-500\">200+ reviews</p>\n                       </div>\n-                      <p className=\"text-sm text-gray-500\">200+ reviews</p>\n                       <div className=\"flex justify-center mt-4 opacity-80\">\n                         <FaJenkins className=\"text-4xl\" />\n                       </div>\n                     </div>\n"
                },
                {
                    "date": 1759922858085,
                    "content": "Index: \n===================================================================\n--- \n+++ \n@@ -41,21 +41,15 @@\n   },\n ];\n \n export default function TestimonialSection() {\n-  const [index, setIndex] = useState(0);\n-  const visibleCount = 4;\n+  const [index, setIndex] = useState(0); // Start from first slide\n+  const visibleCount = 4; // Number of cards visible at a time\n \n-  // Create an extended array for infinite scrolling\n-  const extendedTestimonials = [...testimonials, ...testimonials, ...testimonials];\n-  \n-  // Adjust the index to always point to the middle set for seamless looping\n-  const adjustedIndex = index % testimonials.length;\n-\n   useEffect(() => {\n     const interval = setInterval(() => {\n-      setIndex((prev) => prev + 1);\n-    }, 5000);\n+      setIndex((prev) => (prev + 1) % testimonials.length); // loop\n+    }, 5000); // every 5 seconds\n \n     return () => clearInterval(interval);\n   }, []);\n \n@@ -73,86 +67,62 @@\n         </div>\n \n         {/* Carousel Container */}\n         <div className=\"relative overflow-hidden\">\n+          \n           <div\n-            className=\"flex transition-transform duration-1000 ease-in-out\"\n+            className=\"flex transition-transform duration-1000\"\n             style={{\n-              transform: `translateX(-${index * (100 / visibleCount)}%)`,\n-              width: `${(extendedTestimonials.length * 100) / visibleCount}%`,\n+              transform: `translateX(-${(index * 100) / visibleCount}%)`,\n+              width: `${(testimonials.length * 100) / visibleCount}%`,\n             }}\n           >\n-            {extendedTestimonials.map((t, i) => (\n+               <div className=\"bg-white max-w-[50vh] p-6 shadow-sm text-center  flex flex-col justify-between\">\n+            <div>\n+              <p className=\"text-5xl font-bold text-gray-400\">4.9</p>\n+              <div className=\"flex justify-center my-2\">\n+                {Array(5)\n+                  .fill(null)\n+                  .map((_, i) => (\n+                    <FaStar key={i} className=\"text-green-500\" />\n+                  ))}\n+              </div>\n+              <p className=\"text-sm text-gray-500\">200+ reviews</p>\n+            </div>\n+            <div className=\"flex justify-center mt-4 opacity-80\">\n+              <FaJenkins className=\"text-4xl\" />\n+            </div>\n+          </div>\n+            {testimonials.map((t, i) => (\n               <div\n                 key={i}\n-                className=\"bg-white p-6 shadow-sm flex-shrink-0 flex flex-col justify-between\"\n-                style={{ width: `${100 / visibleCount}%` }}\n+                className=\"bg-white p-6 shadow-sm  flex-shrink-0 flex flex-col justify-between\"\n+                style={{ width: `${100 / testimonials.length}%` }}\n               >\n-                {/* First set - include rating card */}\n-                {i < testimonials.length ? (\n-                  i === 0 ? (\n-                    // Rating card - with same sizing as previous version\n-                    <div className=\"bg-white max-w-[50vh] p-6 shadow-sm text-center flex flex-col justify-between\">\n-                      <div>\n-                        <p className=\"text-5xl font-bold text-gray-400\">4.9</p>\n-                        <div className=\"flex justify-center my-2\">\n-                          {Array(5)\n-                            .fill(null)\n-                            .map((_, starIndex) => (\n-                              <FaStar key={starIndex} className=\"text-green-500\" />\n-                            ))}\n-                        </div>\n-                        <p className=\"text-sm text-gray-500\">200+ reviews</p>\n-                      </div>\n-                      <div className=\"flex justify-center mt-4 opacity-80\">\n-                        <FaJenkins className=\"text-4xl\" />\n-                      </div>\n-                    </div>\n-                  ) : (\n-                    // Regular testimonial cards\n-                    <>\n-                      <p className=\"text-gray-800 text-sm sm:text-base leading-relaxed\">\n-                        {t.quote}\n-                      </p>\n-                      <div className=\"flex items-center mt-4\">\n-                        <div>\n-                          <p className=\"font-bold text-gray-900 text-sm sm:text-base\">\n-                            {t.name}\n-                          </p>\n-                          <p className=\"text-xs sm:text-sm text-gray-500\">{t.title}</p>\n-                        </div>\n-                      </div>\n-                    </>\n-                  )\n-                ) : (\n-                  // Second and third sets - only regular testimonial cards (no rating card)\n-                  <>\n-                    <p className=\"text-gray-800 text-sm sm:text-base leading-relaxed\">\n-                      {t.quote}\n+                <p className=\"text-gray-800 text-sm sm:text-base leading-relaxed\">\n+                  {t.quote}\n+                </p>\n+                <div className=\"flex items-center mt-4\">\n+                  <div>\n+                    <p className=\"font-bold text-gray-900 text-sm sm:text-base\">\n+                      {t.name}\n                     </p>\n-                    <div className=\"flex items-center mt-4\">\n-                      <div>\n-                        <p className=\"font-bold text-gray-900 text-sm sm:text-base\">\n-                          {t.name}\n-                        </p>\n-                        <p className=\"text-xs sm:text-sm text-gray-500\">{t.title}</p>\n-                      </div>\n-                    </div>\n-                  </>\n-                )}\n+                    <p className=\"text-xs sm:text-sm text-gray-500\">{t.title}</p>\n+                  </div>\n+                </div>\n               </div>\n             ))}\n           </div>\n         </div>\n \n         {/* Dots */}\n         <div className=\"flex justify-center mt-10 space-x-2\">\n-          {testimonials.map((_, i) => (\n+          {Array.from({ length: testimonials.length -2 }).map((_, i) => (\n             <button\n               key={i}\n               onClick={() => setIndex(i)}\n               className={`w-3 h-3 rounded-full transition-all ${\n-                adjustedIndex === i ? \"bg-gray-800\" : \"bg-gray-300\"\n+                index === i ? \"bg-gray-800\" : \"bg-gray-300\"\n               }`}\n             ></button>\n           ))}\n         </div>\n"
                },
                {
                    "date": 1759922968870,
                    "content": "Index: \n===================================================================\n--- \n+++ \n@@ -41,19 +41,36 @@\n   },\n ];\n \n export default function TestimonialSection() {\n-  const [index, setIndex] = useState(0); // Start from first slide\n-  const visibleCount = 4; // Number of cards visible at a time\n+  const [index, setIndex] = useState(0);\n+  const visibleCount = 4;\n \n+  // Create infinite loop by duplicating testimonials\n+  const infiniteTestimonials = [...testimonials, ...testimonials, ...testimonials];\n+  \n+  // Calculate the actual index for dot indicators\n+  const actualIndex = index % testimonials.length;\n+\n   useEffect(() => {\n     const interval = setInterval(() => {\n-      setIndex((prev) => (prev + 1) % testimonials.length); // loop\n-    }, 5000); // every 5 seconds\n+      setIndex(prevIndex => prevIndex + 1);\n+    }, 5000);\n \n     return () => clearInterval(interval);\n   }, []);\n \n+  // Reset index to prevent extremely large numbers\n+  useEffect(() => {\n+    if (index >= testimonials.length * 2) {\n+      const timer = setTimeout(() => {\n+        setIndex(index - testimonials.length);\n+      }, 1000); // After transition completes\n+      \n+      return () => clearTimeout(timer);\n+    }\n+  }, [index]);\n+\n   return (\n     <section className=\"relative bg-gray-100 py-12 px-4 sm:px-6 overflow-hidden\">\n       <div className=\"container mx-auto\">\n         {/* Heading */}\n@@ -67,62 +84,68 @@\n         </div>\n \n         {/* Carousel Container */}\n         <div className=\"relative overflow-hidden\">\n-          \n           <div\n-            className=\"flex transition-transform duration-1000\"\n+            className=\"flex transition-transform duration-1000 ease-in-out\"\n             style={{\n               transform: `translateX(-${(index * 100) / visibleCount}%)`,\n-              width: `${(testimonials.length * 100) / visibleCount}%`,\n+              width: `${(infiniteTestimonials.length * 100) / visibleCount}%`,\n             }}\n           >\n-               <div className=\"bg-white max-w-[50vh] p-6 shadow-sm text-center  flex flex-col justify-between\">\n-            <div>\n-              <p className=\"text-5xl font-bold text-gray-400\">4.9</p>\n-              <div className=\"flex justify-center my-2\">\n-                {Array(5)\n-                  .fill(null)\n-                  .map((_, i) => (\n-                    <FaStar key={i} className=\"text-green-500\" />\n-                  ))}\n-              </div>\n-              <p className=\"text-sm text-gray-500\">200+ reviews</p>\n-            </div>\n-            <div className=\"flex justify-center mt-4 opacity-80\">\n-              <FaJenkins className=\"text-4xl\" />\n-            </div>\n-          </div>\n-            {testimonials.map((t, i) => (\n+            {infiniteTestimonials.map((t, i) => (\n               <div\n                 key={i}\n-                className=\"bg-white p-6 shadow-sm  flex-shrink-0 flex flex-col justify-between\"\n-                style={{ width: `${100 / testimonials.length}%` }}\n+                className=\"bg-white p-6 shadow-sm flex-shrink-0 flex flex-col justify-between\"\n+                style={{ width: `${100 / visibleCount}%` }}\n               >\n-                <p className=\"text-gray-800 text-sm sm:text-base leading-relaxed\">\n-                  {t.quote}\n-                </p>\n-                <div className=\"flex items-center mt-4\">\n-                  <div>\n-                    <p className=\"font-bold text-gray-900 text-sm sm:text-base\">\n-                      {t.name}\n+                {/* Show rating card only in the first set */}\n+                {i === 0 ? (\n+                  <div className=\"bg-white max-w-[50vh] p-6 shadow-sm text-center flex flex-col justify-between\">\n+                    <div>\n+                      <p className=\"text-5xl font-bold text-gray-400\">4.9</p>\n+                      <div className=\"flex justify-center my-2\">\n+                        {Array(5)\n+                          .fill(null)\n+                          .map((_, starIndex) => (\n+                            <FaStar key={starIndex} className=\"text-green-500\" />\n+                          ))}\n+                      </div>\n+                      <p className=\"text-sm text-gray-500\">200+ reviews</p>\n+                    </div>\n+                    <div className=\"flex justify-center mt-4 opacity-80\">\n+                      <FaJenkins className=\"text-4xl\" />\n+                    </div>\n+                  </div>\n+                ) : (\n+                  // Show testimonial cards for all other positions\n+                  <>\n+                    <p className=\"text-gray-800 text-sm sm:text-base leading-relaxed\">\n+                      {t.quote}\n                     </p>\n-                    <p className=\"text-xs sm:text-sm text-gray-500\">{t.title}</p>\n-                  </div>\n-                </div>\n+                    <div className=\"flex items-center mt-4\">\n+                      <div>\n+                        <p className=\"font-bold text-gray-900 text-sm sm:text-base\">\n+                          {t.name}\n+                        </p>\n+                        <p className=\"text-xs sm:text-sm text-gray-500\">{t.title}</p>\n+                      </div>\n+                    </div>\n+                  </>\n+                )}\n               </div>\n             ))}\n           </div>\n         </div>\n \n         {/* Dots */}\n         <div className=\"flex justify-center mt-10 space-x-2\">\n-          {Array.from({ length: testimonials.length -2 }).map((_, i) => (\n+          {testimonials.map((_, i) => (\n             <button\n               key={i}\n               onClick={() => setIndex(i)}\n               className={`w-3 h-3 rounded-full transition-all ${\n-                index === i ? \"bg-gray-800\" : \"bg-gray-300\"\n+                actualIndex === i ? \"bg-gray-800\" : \"bg-gray-300\"\n               }`}\n             ></button>\n           ))}\n         </div>\n"
                },
                {
                    "date": 1759923030498,
                    "content": "Index: \n===================================================================\n--- \n+++ \n@@ -95,9 +95,10 @@\n             {infiniteTestimonials.map((t, i) => (\n               <div\n                 key={i}\n                 className=\"bg-white p-6 shadow-sm flex-shrink-0 flex flex-col justify-between\"\n-                style={{ width: `${100 / visibleCount}%` }}\n+                // Fixed the width calculation to match original sizing\n+                style={{ width: `${100 / infiniteTestimonials.length}%` }}\n               >\n                 {/* Show rating card only in the first set */}\n                 {i === 0 ? (\n                   <div className=\"bg-white max-w-[50vh] p-6 shadow-sm text-center flex flex-col justify-between\">\n"
                },
                {
                    "date": 1759923093570,
                    "content": "Index: \n===================================================================\n--- \n+++ \n@@ -41,36 +41,19 @@\n   },\n ];\n \n export default function TestimonialSection() {\n-  const [index, setIndex] = useState(0);\n-  const visibleCount = 4;\n+  const [index, setIndex] = useState(0); // Start from first slide\n+  const visibleCount = 4; // Number of cards visible at a time\n \n-  // Create infinite loop by duplicating testimonials\n-  const infiniteTestimonials = [...testimonials, ...testimonials, ...testimonials];\n-  \n-  // Calculate the actual index for dot indicators\n-  const actualIndex = index % testimonials.length;\n-\n   useEffect(() => {\n     const interval = setInterval(() => {\n-      setIndex(prevIndex => prevIndex + 1);\n-    }, 5000);\n+      setIndex((prev) => (prev + 1) % testimonials.length); // loop\n+    }, 5000); // every 5 seconds\n \n     return () => clearInterval(interval);\n   }, []);\n \n-  // Reset index to prevent extremely large numbers\n-  useEffect(() => {\n-    if (index >= testimonials.length * 2) {\n-      const timer = setTimeout(() => {\n-        setIndex(index - testimonials.length);\n-      }, 1000); // After transition completes\n-      \n-      return () => clearTimeout(timer);\n-    }\n-  }, [index]);\n-\n   return (\n     <section className=\"relative bg-gray-100 py-12 px-4 sm:px-6 overflow-hidden\">\n       <div className=\"container mx-auto\">\n         {/* Heading */}\n@@ -84,69 +67,62 @@\n         </div>\n \n         {/* Carousel Container */}\n         <div className=\"relative overflow-hidden\">\n+          \n           <div\n-            className=\"flex transition-transform duration-1000 ease-in-out\"\n+            className=\"flex transition-transform duration-1000\"\n             style={{\n               transform: `translateX(-${(index * 100) / visibleCount}%)`,\n-              width: `${(infiniteTestimonials.length * 100) / visibleCount}%`,\n+              width: `${(testimonials.length * 100) / visibleCount}%`,\n             }}\n           >\n-            {infiniteTestimonials.map((t, i) => (\n+               <div className=\"bg-white max-w-[50vh] p-6 shadow-sm text-center  flex flex-col justify-between\">\n+            <div>\n+              <p className=\"text-5xl font-bold text-gray-400\">4.9</p>\n+              <div className=\"flex justify-center my-2\">\n+                {Array(5)\n+                  .fill(null)\n+                  .map((_, i) => (\n+                    <FaStar key={i} className=\"text-green-500\" />\n+                  ))}\n+              </div>\n+              <p className=\"text-sm text-gray-500\">200+ reviews</p>\n+            </div>\n+            <div className=\"flex justify-center mt-4 opacity-80\">\n+              <FaJenkins className=\"text-4xl\" />\n+            </div>\n+          </div>\n+            {testimonials.map((t, i) => (\n               <div\n                 key={i}\n-                className=\"bg-white p-6 shadow-sm flex-shrink-0 flex flex-col justify-between\"\n-                // Fixed the width calculation to match original sizing\n-                style={{ width: `${100 / infiniteTestimonials.length}%` }}\n+                className=\"bg-white p-6 shadow-sm  flex-shrink-0 flex flex-col justify-between\"\n+                style={{ width: `${100 / testimonials.length}%` }}\n               >\n-                {/* Show rating card only in the first set */}\n-                {i === 0 ? (\n-                  <div className=\"bg-white max-w-[50vh] p-6 shadow-sm text-center flex flex-col justify-between\">\n-                    <div>\n-                      <p className=\"text-5xl font-bold text-gray-400\">4.9</p>\n-                      <div className=\"flex justify-center my-2\">\n-                        {Array(5)\n-                          .fill(null)\n-                          .map((_, starIndex) => (\n-                            <FaStar key={starIndex} className=\"text-green-500\" />\n-                          ))}\n-                      </div>\n-                      <p className=\"text-sm text-gray-500\">200+ reviews</p>\n-                    </div>\n-                    <div className=\"flex justify-center mt-4 opacity-80\">\n-                      <FaJenkins className=\"text-4xl\" />\n-                    </div>\n+                <p className=\"text-gray-800 text-sm sm:text-base leading-relaxed\">\n+                  {t.quote}\n+                </p>\n+                <div className=\"flex items-center mt-4\">\n+                  <div>\n+                    <p className=\"font-bold text-gray-900 text-sm sm:text-base\">\n+                      {t.name}\n+                    </p>\n+                    <p className=\"text-xs sm:text-sm text-gray-500\">{t.title}</p>\n                   </div>\n-                ) : (\n-                  // Show testimonial cards for all other positions\n-                  <>\n-                    <p className=\"text-gray-800 text-sm sm:text-base leading-relaxed\">\n-                      {t.quote}\n-                    </p>\n-                    <div className=\"flex items-center mt-4\">\n-                      <div>\n-                        <p className=\"font-bold text-gray-900 text-sm sm:text-base\">\n-                          {t.name}\n-                        </p>\n-                        <p className=\"text-xs sm:text-sm text-gray-500\">{t.title}</p>\n-                      </div>\n-                    </div>\n-                  </>\n-                )}\n+                </div>\n               </div>\n             ))}\n           </div>\n         </div>\n \n         {/* Dots */}\n         <div className=\"flex justify-center mt-10 space-x-2\">\n-          {testimonials.map((_, i) => (\n+          {Array.from({ length: testimonials.length -2 }).map((_, i) => (\n             <button\n               key={i}\n               onClick={() => setIndex(i)}\n               className={`w-3 h-3 rounded-full transition-all ${\n-                actualIndex === i ? \"bg-gray-800\" : \"bg-gray-300\"\n+                index === i ? \"bg-gray-800\" : \"bg-gray-300\"\n               }`}\n             ></button>\n           ))}\n         </div>\n"
                },
                {
                    "date": 1759924416205,
                    "content": "Index: \n===================================================================\n--- \n+++ \n@@ -38,8 +38,38 @@\n       \"BKM Global’s approach combines technology, education, and strategy perfectly. Their market alerts and risk management tools help me stay ahead of the curve. It’s not just a trading platform — it’s a complete ecosystem.\",\n     name: \"Sophia L., Forex Enthusiast – Singapore\",\n     title: \"Next-generation trading made simple\",\n   },\n+  {\n+    quote:\n+      \"I’ve been using BKM Global’s investment management service for over a year now. Their strategies are consistent, and the communication is excellent. I receive timely market alerts that actually help me make smarter investment decisions.\",\n+    name: \"Amira K., Investor – Dubai\",\n+    title: \"Reliable and trustworthy investment management\",\n+  },\n+  {\n+    quote:\n+      \"Their Uplearn concept is amazing — I’ve learned so much about forex strategies and market analysis. The team genuinely wants traders to succeed and not just trade blindly. I highly recommend BKM Global for anyone serious about trading.\",\n+    name: \"Rahul S., Beginner Trader – Bengaluru\",\n+    title: \"Best place to learn and grow as a trader\",\n+  },\n+  {\n+    quote:\n+      \"The platform is clean, intuitive, and built with real traders in mind. None match the speed and accuracy of BKM Global’s software. The referral system is also a great bonus!\",\n+    name: \"Fatima Z., Fund Manager – UAE\",\n+    title: \"Transparent, user-friendly, and profitable\",\n+  },\n+  {\n+    quote:\n+      \"The support team is responsive and knowledgeable. They guided me through setting up my first strategy on the algo software, and everything has been smooth since. Their risk management approach makes me feel secure.\",\n+    name: \"Vikram N., Investor – India\",\n+    title: \"Excellent customer support and guidance\",\n+  },\n+  {\n+    quote:\n+      \"BKM Global’s approach combines technology, education, and strategy perfectly. Their market alerts and risk management tools help me stay ahead of the curve. It’s not just a trading platform — it’s a complete ecosystem.\",\n+    name: \"Sophia L., Forex Enthusiast – Singapore\",\n+    title: \"Next-generation trading made simple\",\n+  },\n ];\n \n export default function TestimonialSection() {\n   const [index, setIndex] = useState(0); // Start from first slide\n"
                },
                {
                    "date": 1760061350007,
                    "content": "Index: \n===================================================================\n--- \n+++ \n@@ -1,132 +1,101 @@\n \"use client\";\n import React, { useState, useEffect } from \"react\";\n-import { FaStar, FaJenkins } from \"react-icons/fa\";\n+import { FaStar, FaDatabase } from \"react-icons/fa\";\n \n const testimonials = [\n   {\n     quote:\n-      \"BKM Global has transformed my trading experience. Their algo software is fast, precise, and incredibly efficient. I appreciate how transparent the platform is — I can monitor everything in real-time. It’s a refreshing change from other brokers I’ve used before.\",\n-    name: \"Ramesh P., Independent Trader – India\",\n-    title: \"A truly professional trading partner!\",\n+      \"infod2 has completely streamlined our business analytics process. Their platform makes data insights easy to understand and act upon — saving us hours every week.\",\n+    name: \"Rohit Sharma, Business Analyst – India\",\n+    title: \"Simplified data management and insights\",\n   },\n   {\n     quote:\n-      \"I’ve been using BKM Global’s investment management service for over a year now. Their strategies are consistent, and the communication is excellent. I receive timely market alerts that actually help me make smarter investment decisions.\",\n-    name: \"Amira K., Investor – Dubai\",\n-    title: \"Reliable and trustworthy investment management\",\n+      \"As a small business owner, infod2’s financial dashboard has been a game-changer. I can now track performance, revenue trends, and customer data effortlessly in real-time.\",\n+    name: \"Ananya Mehta, Founder – Delhi\",\n+    title: \"Powerful insights for everyday decisions\",\n   },\n   {\n     quote:\n-      \"Their Uplearn concept is amazing — I’ve learned so much about forex strategies and market analysis. The team genuinely wants traders to succeed and not just trade blindly. I highly recommend BKM Global for anyone serious about trading.\",\n-    name: \"Rahul S., Beginner Trader – Bengaluru\",\n-    title: \"Best place to learn and grow as a trader\",\n+      \"We implemented infod2’s automation tools across multiple departments. The system is reliable, secure, and beautifully designed. It’s everything we needed for our growing team.\",\n+    name: \"James Anderson, Operations Head – Singapore\",\n+    title: \"Reliable and scalable automation platform\",\n   },\n   {\n     quote:\n-      \"The platform is clean, intuitive, and built with real traders in mind. None match the speed and accuracy of BKM Global’s software. The referral system is also a great bonus!\",\n-    name: \"Fatima Z., Fund Manager – UAE\",\n-    title: \"Transparent, user-friendly, and profitable\",\n+      \"infod2 provides the clarity and transparency that our finance team needed. Reports that once took days are now ready in minutes. Highly recommend for data-driven organizations.\",\n+    name: \"Priya Nair, Finance Manager – UAE\",\n+    title: \"Data-driven decisions made simple\",\n   },\n   {\n     quote:\n-      \"The support team is responsive and knowledgeable. They guided me through setting up my first strategy on the algo software, and everything has been smooth since. Their risk management approach makes me feel secure.\",\n-    name: \"Vikram N., Investor – India\",\n-    title: \"Excellent customer support and guidance\",\n+      \"The support team at infod2 is outstanding. They guided us through every setup step and customized dashboards exactly the way we wanted. Excellent experience overall!\",\n+    name: \"Vikram Patel, CTO – India\",\n+    title: \"Exceptional support and customization\",\n   },\n   {\n     quote:\n-      \"BKM Global’s approach combines technology, education, and strategy perfectly. Their market alerts and risk management tools help me stay ahead of the curve. It’s not just a trading platform — it’s a complete ecosystem.\",\n-    name: \"Sophia L., Forex Enthusiast – Singapore\",\n-    title: \"Next-generation trading made simple\",\n+      \"infod2’s analytics suite has helped us identify market patterns and improve business forecasting accuracy. It’s not just a tool, it’s an intelligent partner for growth.\",\n+    name: \"Sophia Lee, Data Strategist – Malaysia\",\n+    title: \"Smart analytics for smarter business\",\n   },\n-  {\n-    quote:\n-      \"I’ve been using BKM Global’s investment management service for over a year now. Their strategies are consistent, and the communication is excellent. I receive timely market alerts that actually help me make smarter investment decisions.\",\n-    name: \"Amira K., Investor – Dubai\",\n-    title: \"Reliable and trustworthy investment management\",\n-  },\n-  {\n-    quote:\n-      \"Their Uplearn concept is amazing — I’ve learned so much about forex strategies and market analysis. The team genuinely wants traders to succeed and not just trade blindly. I highly recommend BKM Global for anyone serious about trading.\",\n-    name: \"Rahul S., Beginner Trader – Bengaluru\",\n-    title: \"Best place to learn and grow as a trader\",\n-  },\n-  {\n-    quote:\n-      \"The platform is clean, intuitive, and built with real traders in mind. None match the speed and accuracy of BKM Global’s software. The referral system is also a great bonus!\",\n-    name: \"Fatima Z., Fund Manager – UAE\",\n-    title: \"Transparent, user-friendly, and profitable\",\n-  },\n-  {\n-    quote:\n-      \"The support team is responsive and knowledgeable. They guided me through setting up my first strategy on the algo software, and everything has been smooth since. Their risk management approach makes me feel secure.\",\n-    name: \"Vikram N., Investor – India\",\n-    title: \"Excellent customer support and guidance\",\n-  },\n-  {\n-    quote:\n-      \"BKM Global’s approach combines technology, education, and strategy perfectly. Their market alerts and risk management tools help me stay ahead of the curve. It’s not just a trading platform — it’s a complete ecosystem.\",\n-    name: \"Sophia L., Forex Enthusiast – Singapore\",\n-    title: \"Next-generation trading made simple\",\n-  },\n ];\n \n export default function TestimonialSection() {\n-  const [index, setIndex] = useState(0); // Start from first slide\n-  const visibleCount = 4; // Number of cards visible at a time\n+  const [index, setIndex] = useState(0);\n+  const visibleCount = 4;\n \n   useEffect(() => {\n     const interval = setInterval(() => {\n-      setIndex((prev) => (prev + 1) % testimonials.length); // loop\n-    }, 5000); // every 5 seconds\n-\n+      setIndex((prev) => (prev + 1) % testimonials.length);\n+    }, 5000);\n     return () => clearInterval(interval);\n   }, []);\n \n   return (\n-    <section className=\"relative bg-gray-100 py-12 px-4 sm:px-6 overflow-hidden\">\n+    <section className=\"relative bg-gray-50 py-12 px-4 sm:px-6 overflow-hidden\">\n       <div className=\"container mx-auto\">\n         {/* Heading */}\n         <div className=\"text-center mb-10\">\n           <h2 className=\"text-3xl sm:text-5xl font-bold text-gray-900 leading-snug\">\n-            Find your best Support with us.\n+            Hear from Our Valued Clients\n           </h2>\n           <p className=\"text-lg sm:text-2xl text-gray-600 font-semibold mt-3\">\n-            We guarantee your next success!\n+            Empowering businesses through intelligent data solutions\n           </p>\n         </div>\n \n-        {/* Carousel Container */}\n+        {/* Carousel */}\n         <div className=\"relative overflow-hidden\">\n-          \n           <div\n             className=\"flex transition-transform duration-1000\"\n             style={{\n               transform: `translateX(-${(index * 100) / visibleCount}%)`,\n               width: `${(testimonials.length * 100) / visibleCount}%`,\n             }}\n           >\n-               <div className=\"bg-white max-w-[50vh] p-6 shadow-sm text-center  flex flex-col justify-between\">\n-            <div>\n-              <p className=\"text-5xl font-bold text-gray-400\">4.9</p>\n-              <div className=\"flex justify-center my-2\">\n-                {Array(5)\n-                  .fill(null)\n-                  .map((_, i) => (\n-                    <FaStar key={i} className=\"text-green-500\" />\n-                  ))}\n+            <div className=\"bg-white max-w-[50vh] p-6 shadow-sm text-center flex flex-col justify-between\">\n+              <div>\n+                <p className=\"text-5xl font-bold text-gray-400\">4.9</p>\n+                <div className=\"flex justify-center my-2\">\n+                  {Array(5)\n+                    .fill(null)\n+                    .map((_, i) => (\n+                      <FaStar key={i} className=\"text-green-500\" />\n+                    ))}\n+                </div>\n+                <p className=\"text-sm text-gray-500\">250+ verified reviews</p>\n               </div>\n-              <p className=\"text-sm text-gray-500\">200+ reviews</p>\n+              <div className=\"flex justify-center mt-4 opacity-80\">\n+                <FaDatabase className=\"text-4xl\" />\n+              </div>\n             </div>\n-            <div className=\"flex justify-center mt-4 opacity-80\">\n-              <FaJenkins className=\"text-4xl\" />\n-            </div>\n-          </div>\n+\n             {testimonials.map((t, i) => (\n               <div\n                 key={i}\n-                className=\"bg-white p-6 shadow-sm  flex-shrink-0 flex flex-col justify-between\"\n+                className=\"bg-white p-6 shadow-sm flex-shrink-0 flex flex-col justify-between\"\n                 style={{ width: `${100 / testimonials.length}%` }}\n               >\n                 <p className=\"text-gray-800 text-sm sm:text-base leading-relaxed\">\n                   {t.quote}\n@@ -145,9 +114,9 @@\n         </div>\n \n         {/* Dots */}\n         <div className=\"flex justify-center mt-10 space-x-2\">\n-          {Array.from({ length: testimonials.length -2 }).map((_, i) => (\n+          {Array.from({ length: testimonials.length - 2 }).map((_, i) => (\n             <button\n               key={i}\n               onClick={() => setIndex(i)}\n               className={`w-3 h-3 rounded-full transition-all ${\n@@ -158,5 +127,5 @@\n         </div>\n       </div>\n     </section>\n   );\n-}\n\\ No newline at end of file\n+}\n"
                },
                {
                    "date": 1760061365021,
                    "content": "Index: \n===================================================================\n--- \n+++ \n@@ -4,39 +4,39 @@\n \n const testimonials = [\n   {\n     quote:\n-      \"infod2 has completely streamlined our business analytics process. Their platform makes data insights easy to understand and act upon — saving us hours every week.\",\n+      \"InfoD has completely streamlined our business analytics process. Their platform makes data insights easy to understand and act upon — saving us hours every week.\",\n     name: \"Rohit Sharma, Business Analyst – India\",\n     title: \"Simplified data management and insights\",\n   },\n   {\n     quote:\n-      \"As a small business owner, infod2’s financial dashboard has been a game-changer. I can now track performance, revenue trends, and customer data effortlessly in real-time.\",\n+      \"As a small business owner, InfoD’s financial dashboard has been a game-changer. I can now track performance, revenue trends, and customer data effortlessly in real-time.\",\n     name: \"Ananya Mehta, Founder – Delhi\",\n     title: \"Powerful insights for everyday decisions\",\n   },\n   {\n     quote:\n-      \"We implemented infod2’s automation tools across multiple departments. The system is reliable, secure, and beautifully designed. It’s everything we needed for our growing team.\",\n+      \"We implemented InfoD’s automation tools across multiple departments. The system is reliable, secure, and beautifully designed. It’s everything we needed for our growing team.\",\n     name: \"James Anderson, Operations Head – Singapore\",\n     title: \"Reliable and scalable automation platform\",\n   },\n   {\n     quote:\n-      \"infod2 provides the clarity and transparency that our finance team needed. Reports that once took days are now ready in minutes. Highly recommend for data-driven organizations.\",\n+      \"InfoD provides the clarity and transparency that our finance team needed. Reports that once took days are now ready in minutes. Highly recommend for data-driven organizations.\",\n     name: \"Priya Nair, Finance Manager – UAE\",\n     title: \"Data-driven decisions made simple\",\n   },\n   {\n     quote:\n-      \"The support team at infod2 is outstanding. They guided us through every setup step and customized dashboards exactly the way we wanted. Excellent experience overall!\",\n+      \"The support team at InfoD is outstanding. They guided us through every setup step and customized dashboards exactly the way we wanted. Excellent experience overall!\",\n     name: \"Vikram Patel, CTO – India\",\n     title: \"Exceptional support and customization\",\n   },\n   {\n     quote:\n-      \"infod2’s analytics suite has helped us identify market patterns and improve business forecasting accuracy. It’s not just a tool, it’s an intelligent partner for growth.\",\n+      \"InfoD’s analytics suite has helped us identify market patterns and improve business forecasting accuracy. It’s not just a tool, it’s an intelligent partner for growth.\",\n     name: \"Sophia Lee, Data Strategist – Malaysia\",\n     title: \"Smart analytics for smarter business\",\n   },\n ];\n"
                }
            ],
            "date": 1759922531298,
            "name": "Commit-0",
            "content": "\"use client\";\nimport React, { useState, useEffect } from \"react\";\nimport { FaStar, FaJenkins } from \"react-icons/fa\";\n\nconst testimonials = [\n  {\n    quote:\n      \"BKM Global has transformed my trading experience. Their algo software is fast, precise, and incredibly efficient. I appreciate how transparent the platform is — I can monitor everything in real-time. It’s a refreshing change from other brokers I’ve used before.\",\n    name: \"Ramesh P., Independent Trader – India\",\n    title: \"A truly professional trading partner!\",\n  },\n  {\n    quote:\n      \"I’ve been using BKM Global’s investment management service for over a year now. Their strategies are consistent, and the communication is excellent. I receive timely market alerts that actually help me make smarter investment decisions.\",\n    name: \"Amira K., Investor – Dubai\",\n    title: \"Reliable and trustworthy investment management\",\n  },\n  {\n    quote:\n      \"Their Uplearn concept is amazing — I’ve learned so much about forex strategies and market analysis. The team genuinely wants traders to succeed and not just trade blindly. I highly recommend BKM Global for anyone serious about trading.\",\n    name: \"Rahul S., Beginner Trader – Bengaluru\",\n    title: \"Best place to learn and grow as a trader\",\n  },\n  {\n    quote:\n      \"The platform is clean, intuitive, and built with real traders in mind. None match the speed and accuracy of BKM Global’s software. The referral system is also a great bonus!\",\n    name: \"Fatima Z., Fund Manager – UAE\",\n    title: \"Transparent, user-friendly, and profitable\",\n  },\n  {\n    quote:\n      \"The support team is responsive and knowledgeable. They guided me through setting up my first strategy on the algo software, and everything has been smooth since. Their risk management approach makes me feel secure.\",\n    name: \"Vikram N., Investor – India\",\n    title: \"Excellent customer support and guidance\",\n  },\n  {\n    quote:\n      \"BKM Global’s approach combines technology, education, and strategy perfectly. Their market alerts and risk management tools help me stay ahead of the curve. It’s not just a trading platform — it’s a complete ecosystem.\",\n    name: \"Sophia L., Forex Enthusiast – Singapore\",\n    title: \"Next-generation trading made simple\",\n  },\n];\n\nexport default function TestimonialSection() {\n  const [index, setIndex] = useState(0);\n  const visibleCount = 4;\n\n  // Create an extended array for infinite scrolling\n  const extendedTestimonials = [...testimonials, ...testimonials, ...testimonials];\n  \n  // Adjust the index to always point to the middle set for seamless looping\n  const adjustedIndex = index % testimonials.length;\n\n  useEffect(() => {\n    const interval = setInterval(() => {\n      setIndex((prev) => prev + 1);\n    }, 5000);\n\n    return () => clearInterval(interval);\n  }, []);\n\n  return (\n    <section className=\"relative bg-gray-100 py-12 px-4 sm:px-6 overflow-hidden\">\n      <div className=\"container mx-auto\">\n        {/* Heading */}\n        <div className=\"text-center mb-10\">\n          <h2 className=\"text-3xl sm:text-5xl font-bold text-gray-900 leading-snug\">\n            Find your best Support with us.\n          </h2>\n          <p className=\"text-lg sm:text-2xl text-gray-600 font-semibold mt-3\">\n            We guarantee your next success!\n          </p>\n        </div>\n\n        {/* Carousel Container */}\n        <div className=\"relative overflow-hidden\">\n          <div\n            className=\"flex transition-transform duration-1000 ease-in-out\"\n            style={{\n              transform: `translateX(-${index * (100 / visibleCount)}%)`,\n              width: `${(extendedTestimonials.length * 100) / visibleCount}%`,\n            }}\n          >\n            {extendedTestimonials.map((t, i) => (\n              <div\n                key={i}\n                className=\"bg-white p-6 shadow-sm flex-shrink-0 flex flex-col justify-between\"\n                style={{ width: `${100 / visibleCount}%` }}\n              >\n                {/* First set - include rating card */}\n                {i < testimonials.length ? (\n                  i === 0 ? (\n                    // Rating card\n                    <div className=\"text-center\">\n                      <p className=\"text-5xl font-bold text-gray-400\">4.9</p>\n                      <div className=\"flex justify-center my-2\">\n                        {[...Array(5)].map((_, starIndex) => (\n                          <FaStar key={starIndex} className=\"text-green-500\" />\n                        ))}\n                      </div>\n                      <p className=\"text-sm text-gray-500\">200+ reviews</p>\n                      <div className=\"flex justify-center mt-4 opacity-80\">\n                        <FaJenkins className=\"text-4xl\" />\n                      </div>\n                    </div>\n                  ) : (\n                    // Regular testimonial cards\n                    <>\n                      <p className=\"text-gray-800 text-sm sm:text-base leading-relaxed\">\n                        {t.quote}\n                      </p>\n                      <div className=\"flex items-center mt-4\">\n                        <div>\n                          <p className=\"font-bold text-gray-900 text-sm sm:text-base\">\n                            {t.name}\n                          </p>\n                          <p className=\"text-xs sm:text-sm text-gray-500\">{t.title}</p>\n                        </div>\n                      </div>\n                    </>\n                  )\n                ) : (\n                  // Second and third sets - only regular testimonial cards (no rating card)\n                  <>\n                    <p className=\"text-gray-800 text-sm sm:text-base leading-relaxed\">\n                      {t.quote}\n                    </p>\n                    <div className=\"flex items-center mt-4\">\n                      <div>\n                        <p className=\"font-bold text-gray-900 text-sm sm:text-base\">\n                          {t.name}\n                        </p>\n                        <p className=\"text-xs sm:text-sm text-gray-500\">{t.title}</p>\n                      </div>\n                    </div>\n                  </>\n                )}\n              </div>\n            ))}\n          </div>\n        </div>\n\n        {/* Dots */}\n        <div className=\"flex justify-center mt-10 space-x-2\">\n          {testimonials.map((_, i) => (\n            <button\n              key={i}\n              onClick={() => setIndex(i)}\n              className={`w-3 h-3 rounded-full transition-all ${\n                adjustedIndex === i ? \"bg-gray-800\" : \"bg-gray-300\"\n              }`}\n            ></button>\n          ))}\n        </div>\n      </div>\n    </section>\n  );\n}"
        }
    ]
}